Metadata-Version: 2.1
Name: simple_linear_regressionHiba
Version: 1.0.0
Summary: An awesome package that does something
Home-page: http://pypi.python.org/pypi/simple_linear_regressionHiba/
Author: OUCHENE HibetElrahamne
Author-email: hibaouchene51@gmail.com
License: LICENSE.txt
License-File: LICENSE.txt
